pynaads/__init__.py
pynaads/event.py
pynaads/naads.py
pynaads-1.0.0.dist-info/LICENSE
pynaads-1.0.0.dist-info/METADATA
pynaads-1.0.0.dist-info/WHEEL
pynaads-1.0.0.dist-info/top_level.txt
pynaads-1.0.0.dist-info/RECORD
