Metadata-Version: 2.1
Name: pynaads
Version: 1.0.0
Summary: Python library to monitor Pelmorex's NAADS service
Home-page: https://github.com/VE3LSR/pynaads
Author: VE3LSR / VE3YCA
Author-email: projects@ve3lsr.ca
License: UNKNOWN
Platform: UNKNOWN
Classifier: Programming Language :: Python :: 3
Classifier: Operating System :: OS Independent
Requires-Dist: shapely
Requires-Dist: xmltodict
Requires-Dist: numpy
Requires-Dist: geog
Requires-Dist: geojson
